<?xml version="1.0" encoding="UTF-8" ?>
<!DOCTYPE mapper PUBLIC "-//mybatis.org//DTD Mapper 3.0//EN" "http://mybatis.org/dtd/mybatis-3-mapper.dtd" >
<mapper namespace="com.amwang.biz.serverModel.dao.TbeisaiDataDao">
	<resultMap id="BaseResultMap"
		type="com.amwang.biz.serverModel.entity.TbeisaiData">
		<result column="id" property="id" jdbcType="DECIMAL" />
		<result column="OPEN_DATE" property="opendate"
			jdbcType="VARCHAR" />
		<result column="TEXT_NO" property="textno" jdbcType="VARCHAR" />
		<result column="NUM1" property="num1" jdbcType="VARCHAR" />
		<result column="NUM2" property="num2" jdbcType="VARCHAR" />
		<result column="NUM3" property="num3" jdbcType="VARCHAR" />
		<result column="NUM4" property="num4" jdbcType="VARCHAR" />
		<result column="NUM5" property="num5" jdbcType="VARCHAR" />
		<result column="NUM6" property="num6" jdbcType="VARCHAR" />
		<result column="NUM7" property="num7" jdbcType="VARCHAR" />
		<result column="NUM8" property="num8" jdbcType="VARCHAR" />
		<result column="NUM9" property="num9" jdbcType="VARCHAR" />
		<result column="NUM10" property="num10" jdbcType="VARCHAR" />
		<result column="SUM" property="sum" jdbcType="VARCHAR" />
		<result column="BIGORSMALL" property="bigOrSmall"
			jdbcType="VARCHAR" />
		<result column="SINGLEORDOUBLE" property="singleOrDouble"
			jdbcType="VARCHAR" />
		<result column="CREATE_TIME" property="createTime"
			jdbcType="VARCHAR" />
		<result column="REMARK" property="remark" jdbcType="VARCHAR" />
	</resultMap>

	<sql id="Base_Column_List">
		id,TEXT_NO,SUM,SINGLEORDOUBLE,REMARK,OPEN_DATE,NUM9,NUM8,NUM7,NUM6,NUM5,NUM4,NUM3,NUM2,NUM10,NUM1
	</sql>
	<!-- 汇总每个名次 -->
	<select id="sumNums" resultMap="BaseResultMap">
		SELECT *
		FROM T_BEISAI_DATA t
		WHERE 1 = 1 
		ORDER BY t.TEXT_NO desc
		limit #{min}
	</select>
	
	<select id="queryBySum" resultMap="BaseResultMap">
		select * from T_BEISAI_DATA
		where sum is null
	</select>
	<select id="sumEachNum"
		resultType="com.amwang.biz.serverModel.entity.SumEachNum">
		SELECT t.NUM1 num , count(*) con from T_BEISAI_DATA t group
		by t.NUM1 order by t.NUM1
	</select>
	<select id="sumAllCounts" resultType="decimal">
		select count(*) from
		T_BEISAI_DATA
	</select>
	<select id="queryMaxTextno" resultType="string">
		select TEXT_NO from
		T_BEISAI_DATA ORDER BY id desc limit 1
	</select>
	<select id="queryRecordByTextNo" resultType="int">
		select count(*) from
		T_BEISAI_DATA WHERE TEXT_NO = #{textno}
	</select>

	<insert id="addRecord"
		parameterType="com.amwang.biz.serverModel.entity.TbeisaiData"
		keyProperty="id" useGeneratedKeys="true">
		insert into T_BEISAI_DATA
		<trim prefix="(" suffix=")" suffixOverrides=",">
			<!-- <if test="id != null"> -->
			<!-- id, -->
			<!-- </if> -->
			<if test="opendate != null">
				OPEN_DATE,
			</if>
			<if test="textno != null">
				TEXT_NO,
			</if>
			<if test="num1 != null">
				NUM1,
			</if>
			<if test="num2 != null">
				NUM2,
			</if>
			<if test="num3 != null">
				NUM3,
			</if>
			<if test="num4 != null">
				NUM4,
			</if>
			<if test="num5 != null">
				NUM5,
			</if>
			<if test="num6 != null">
				NUM6,
			</if>
			<if test="num7 != null">
				NUM7,
			</if>
			<if test="num8 != null">
				NUM8,
			</if>
			<if test="num9 != null">
				NUM9,
			</if>
			<if test="num10 != null">
				NUM10,
			</if>
			<if test="sum != null">
				SUM,
			</if>
			<if test="bigOrSmall != null">
				BIGORSMALL,
			</if>
			<if test="singleOrDouble != null">
				SINGLEORDOUBLE,
			</if>
			<if test="createTime != null">
				CREATE_TIME,
			</if>
			<if test="remark != null">
				REMARK,
			</if>
		</trim>
		<trim prefix="values (" suffix=")" suffixOverrides=",">
			<!-- <if test="id != null"> -->
			<!-- #{id,jdbcType=VARCHAR}, -->
			<!-- </if> -->
			<if test="opendate != null">
				#{opendate,jdbcType=VARCHAR},
			</if>
			<if test="textno != null">
				#{textno,jdbcType=VARCHAR},
			</if>
			<if test="num1 != null">
				#{num1,jdbcType=VARCHAR},
			</if>
			<if test="num2 != null">
				#{num2,jdbcType=VARCHAR},
			</if>
			<if test="num3 != null">
				#{num3,jdbcType=VARCHAR},
			</if>
			<if test="num4 != null">
				#{num4,jdbcType=VARCHAR},
			</if>
			<if test="num5 != null">
				#{num5,jdbcType=VARCHAR},
			</if>
			<if test="num6 != null">
				#{num6,jdbcType=VARCHAR},
			</if>
			<if test="num7 != null">
				#{num7,jdbcType=VARCHAR},
			</if>
			<if test="num8 != null">
				#{num8,jdbcType=VARCHAR},
			</if>
			<if test="num9 != null">
				#{num9,jdbcType=VARCHAR},
			</if>
			<if test="num10 != null">
				#{num10,jdbcType=VARCHAR},
			</if>
			<if test="sum != null">
				#{sum,jdbcType=VARCHAR},
			</if>
			<if test="bigOrSmall != null">
				#{bigOrSmall,jdbcType=VARCHAR},
			</if>
			<if test="singleOrDouble != null">
				#{singleOrDouble,jdbcType=VARCHAR},
			</if>
			<if test="createTime != null">
				#{createTime,jdbcType=VARCHAR},
			</if>
			<if test="remark != null">
				#{remark,jdbcType=VARCHAR},
			</if>
		</trim>
	</insert>
	<update id="updateRecord">
		update T_BEISAI_DATA
		<set>
			<if test="sum != null">
				SUM = #{sum,jdbcType=VARCHAR},
			</if>
			<if test="bigOrSmall != null">
				BIGORSMALL = #{bigOrSmall,jdbcType=VARCHAR},
			</if>
			<if test="singleOrDouble != null">
				SINGLEORDOUBLE = #{singleOrDouble,jdbcType=VARCHAR},
			</if>
		</set>
		where TEXT_NO = #{textno,jdbcType=VARCHAR}
	</update>
</mapper>